dualxda/__init__.py
dualxda/dualda.py
dualxda/utils.py
dualxda-0.1.0.dist-info/licenses/LICENSE
dualxda-0.1.0.dist-info/METADATA
dualxda-0.1.0.dist-info/WHEEL
dualxda-0.1.0.dist-info/top_level.txt
dualxda-0.1.0.dist-info/RECORD
